colorgb/__init__.py
colorgb/backgrounds.py
colorgb/dictionary.py
colorgb/errors.py
colorgb/foregrounds.py
colorgb/styles.py
colorgb-4.1.dist-info/LICENSE
colorgb-4.1.dist-info/METADATA
colorgb-4.1.dist-info/WHEEL
colorgb-4.1.dist-info/top_level.txt
colorgb-4.1.dist-info/RECORD
