Metadata-Version: 2.1
Name: colorgb
Version: 4.1
Summary: A Python packages to coloring and styling default terminal text
Home-page: https://github.com/LyQuid12/colorgb
Author: LyQuid
Author-email: lyquidpersonal@gmail.com
License: MIT License
Project-URL: Source Code, https://github.com/LyQuid12/colorgb
Project-URL: Discord, https://discord.gg/qpT2AeYZRN
Project-URL: Issue tracker, https://github.com/LyQuid12/colorgb/issues
Keywords: python,color,colorgb,coloring,recoloring,rgb
Classifier: Development Status :: 5 - Production/Stable
Classifier: Intended Audience :: Education
Classifier: Programming Language :: Python :: 3.7
Classifier: Programming Language :: Python :: 3.8
Classifier: Programming Language :: Python :: 3.9
Classifier: Programming Language :: Python :: 3.10
Classifier: License :: OSI Approved :: MIT License
Classifier: Operating System :: Microsoft :: Windows
Classifier: Operating System :: MacOS
Classifier: Operating System :: POSIX :: Linux
Classifier: Operating System :: Android
License-File: LICENSE
Requires-Dist: colorama (==0.4.4)
